reacttools/__init__.py
reacttools/admin.py
reacttools/apps.py
reacttools/models.py
reacttools/tests.py
reacttools/urls.py
reacttools/views.py
reacttools/management/__init__.py
reacttools/management/commands/__init__.py
reacttools/management/commands/collectreact.py
reacttools/migrations/0001_initial.py
reacttools/migrations/0002_auto_20190612_1911.py
reacttools/migrations/0003_reactappsettings_build_path.py
reacttools/migrations/0004_auto_20190612_1923.py
reacttools/migrations/0005_reactappsettings_build_cmd.py
reacttools/migrations/0006_auto_20190612_2054.py
reacttools/migrations/0007_auto_20190612_2059.py
reacttools/migrations/0008_reactappsettings_static_path_prefix.py
reacttools/migrations/0009_auto_20190612_2113.py
reacttools/migrations/0010_auto_20190612_2123.py
reacttools/migrations/0011_reactappsettings_react_root.py
reacttools/migrations/0012_auto_20210930_1120.py
reacttools/migrations/__init__.py
django_react_tools-0.4.7.dist-info/LICENSE
django_react_tools-0.4.7.dist-info/METADATA
django_react_tools-0.4.7.dist-info/WHEEL
django_react_tools-0.4.7.dist-info/top_level.txt
django_react_tools-0.4.7.dist-info/RECORD
