Metadata-Version: 2.1
Name: django-react-tools
Version: 0.4.7
Summary: Tools for helping integrate ReactJS into a Django project.
Author: Devon Jackson
Author-email: Grant Viklund <renderbox@gmail.com>
Project-URL: Homepage, https://github.com/renderbox/django-react-tools
Project-URL: Bug Tracker, https://github.com/renderbox/django-react-tools/issues
Keywords: django,app
Classifier: Development Status :: 4 - Beta
Classifier: Intended Audience :: Developers
Classifier: Programming Language :: Python :: 3 :: Only
Classifier: Programming Language :: Python :: 3.11
Classifier: Programming Language :: Python :: 3.12
Classifier: Programming Language :: Python :: 3.13
Requires-Python: >=3.11
License-File: LICENSE
Requires-Dist: Django<5.2,>=4.1
Requires-Dist: requests
Provides-Extra: dev
Requires-Dist: black; extra == "dev"
Requires-Dist: flake8; extra == "dev"
Requires-Dist: flake8-black; extra == "dev"
Requires-Dist: mypy; extra == "dev"
Requires-Dist: bandit; extra == "dev"
Requires-Dist: isort; extra == "dev"
Requires-Dist: toml; extra == "dev"
Provides-Extra: docs
Requires-Dist: coverage; extra == "docs"
Provides-Extra: test
Requires-Dist: black; extra == "test"
Requires-Dist: flake8; extra == "test"
Requires-Dist: flake8-black; extra == "test"
Requires-Dist: mypy; extra == "test"
Requires-Dist: bandit; extra == "test"
Requires-Dist: isort; extra == "test"
Requires-Dist: coverage; extra == "test"
